MANIFEST.in
README.rst
setup.py
yell/__init__.py
yell/decorators.py
yell/registry.py
yell/tests.py
yell.egg-info/PKG-INFO
yell.egg-info/SOURCES.txt
yell.egg-info/dependency_links.txt
yell.egg-info/top_level.txt
yell/backends/__init__.py
yell/backends/celery.py
yell/backends/django.py