Metadata-Version: 1.0
Name: yell
Version: 0.3
Summary: User notification library with pluggable backends. Compatible with popular frameworks such as Django, Flask, Celery.
Home-page: https://github.com/caffeinehit/yell
Author: Alen Mujezinovic
Author-email: flashingpumpkin@gmail.com
License: UNKNOWN
Keywords: django flask celery user notifications yell buffalo
Platform: UNKNOWN
Classifier: Development Status :: 5 - Production/Stable
Classifier: Environment :: Console
Classifier: Environment :: MacOS X
Classifier: Environment :: Web Environment
Classifier: Environment :: Other Environment
Classifier: Environment :: X11 Applications
Classifier: Framework :: Django
Classifier: Framework :: Paste
Classifier: Framework :: Pylons
Classifier: Framework :: TurboGears
Classifier: Framework :: Twisted
Classifier: Intended Audience :: Developers
Classifier: Operating System :: OS Independent
Classifier: Programming Language :: Python
Classifier: Topic :: Communications
Classifier: Topic :: Communications :: Email
Classifier: Topic :: Database
Classifier: Topic :: Internet :: WWW/HTTP :: Dynamic Content
Classifier: Topic :: Software Development :: Libraries :: Application Frameworks
Classifier: Topic :: Software Development :: Libraries :: Python Modules
Classifier: Topic :: Utilities
